adafruit_circuitpython_mcp2515-1.1.11.dist-info/licenses/LICENSE
adafruit_mcp2515/__init__.py
adafruit_mcp2515/timer.py
adafruit_mcp2515/canio/__init__.py
adafruit_circuitpython_mcp2515-1.1.11.dist-info/METADATA
adafruit_circuitpython_mcp2515-1.1.11.dist-info/WHEEL
adafruit_circuitpython_mcp2515-1.1.11.dist-info/top_level.txt
adafruit_circuitpython_mcp2515-1.1.11.dist-info/RECORD
