Metadata-Version: 2.4
Name: adafruit-circuitpython-mcp2515
Version: 1.1.11
Summary: A CircuitPython library for working with the MCP2515 CAN bus controller
Author-email: Adafruit Industries <circuitpython@adafruit.com>
License: MIT
Project-URL: Homepage, https://github.com/adafruit/Adafruit_CircuitPython_MCP2515
Keywords: adafruit,blinka,circuitpython,micropython,mcp2515,CAN,CANBUS,OBD
Classifier: Intended Audience :: Developers
Classifier: Topic :: Software Development :: Libraries
Classifier: Topic :: Software Development :: Embedded Systems
Classifier: Topic :: System :: Hardware
Classifier: License :: OSI Approved :: MIT License
Classifier: Programming Language :: Python :: 3
License-File: LICENSE
Requires-Dist: Adafruit-Blinka
Requires-Dist: adafruit-circuitpython-busdevice
Provides-Extra: optional
Dynamic: license-file
